tropass_sdk/__init__.py
tropass_sdk-0.1.3.dist-info/licenses/LICENSE
tropass_sdk-0.1.3.dist-info/METADATA
tropass_sdk-0.1.3.dist-info/WHEEL
tropass_sdk-0.1.3.dist-info/top_level.txt
tropass_sdk-0.1.3.dist-info/RECORD
