Metadata-Version: 2.4
Name: tropass-sdk
Version: 0.1.3
Summary: Tropass SDK helps you develop and manage your models for Tropass platform
Keywords: python,ai,tropass,models,ai-model,ai-sdk,python-sdk,llm
Classifier: Typing :: Typed
Classifier: Topic :: Software Development :: Build Tools
Classifier: Operating System :: MacOS
Classifier: Operating System :: Microsoft
Classifier: Operating System :: POSIX :: Linux
Classifier: Intended Audience :: Developers
Classifier: Programming Language :: Python
Classifier: Programming Language :: Python :: 3
Classifier: Programming Language :: Python :: 3 :: Only
Classifier: Programming Language :: Python :: 3.10
Classifier: Programming Language :: Python :: 3.11
Classifier: Programming Language :: Python :: 3.12
Classifier: Programming Language :: Python :: 3.13
Classifier: Programming Language :: Python :: 3.14
Requires-Python: <4,>=3.10
License-File: LICENSE
Dynamic: license-file
